ifnepitope2/blast_binaries/linux/blastp
ifnepitope2/blast_binaries/mac/blastp
ifnepitope2/blast_binaries/windows/blastp.exe
ifnepitope2/blast_binaries/windows/nghttp2.dll
ifnepitope2/blast_db/human_db.pdb
ifnepitope2/blast_db/human_db.phr
ifnepitope2/blast_db/human_db.pin
ifnepitope2/blast_db/human_db.pog
ifnepitope2/blast_db/human_db.pos
ifnepitope2/blast_db/human_db.pot
ifnepitope2/blast_db/human_db.psq
ifnepitope2/blast_db/human_db.ptf
ifnepitope2/blast_db/human_db.pto
ifnepitope2/blast_db/mouse_db.pdb
ifnepitope2/blast_db/mouse_db.phr
ifnepitope2/blast_db/mouse_db.pin
ifnepitope2/blast_db/mouse_db.pog
ifnepitope2/blast_db/mouse_db.pos
ifnepitope2/blast_db/mouse_db.pot
ifnepitope2/blast_db/mouse_db.psq
ifnepitope2/blast_db/mouse_db.ptf
ifnepitope2/blast_db/mouse_db.pto
ifnepitope2/model/human_et.pkl
ifnepitope2/model/mouse_et.pkl
ifnepitope2/python_scripts/__init__.py
ifnepitope2/python_scripts/ifnepitope2.py
ifnepitope2-1.2.dist-info/METADATA
ifnepitope2-1.2.dist-info/WHEEL
ifnepitope2-1.2.dist-info/entry_points.txt
ifnepitope2-1.2.dist-info/top_level.txt
ifnepitope2-1.2.dist-info/RECORD
