Metadata-Version: 2.1
Name: ifnepitope2
Version: 1.2
Summary: A tool to predict ifn inducing epitopes
Home-page: https://github.com/raghavagps/ifnepitope2
Requires-Python: >=3.6
Requires-Dist: numpy
Requires-Dist: pandas (==1.4.0)
Requires-Dist: tqdm
Requires-Dist: scikit-learn (==1.2.1)
